pydantic_openapi_helper/__init__.py
pydantic_openapi_helper/core.py
pydantic_openapi_helper/helper.py
pydantic_openapi_helper/inheritance.py
pydantic_openapi_helper-0.2.11.dist-info/LICENSE
pydantic_openapi_helper-0.2.11.dist-info/METADATA
pydantic_openapi_helper-0.2.11.dist-info/WHEEL
pydantic_openapi_helper-0.2.11.dist-info/top_level.txt
pydantic_openapi_helper-0.2.11.dist-info/RECORD
