Metadata-Version: 2.1
Name: pydantic-openapi-helper
Version: 0.2.11
Summary: A small module to add additional post-processing to the OpenAPI schemas that are generated by Pydantic.
Home-page: https://github.com/ladybug-tools/pydantic-openapi-helper
Author: Ladybug Tools
Author-email: info@ladybug.tools
License: MIT
Classifier: Programming Language :: Python :: 3.7
Classifier: Programming Language :: Python :: Implementation :: CPython
Classifier: License :: OSI Approved :: MIT License
Classifier: Operating System :: OS Independent
License-File: LICENSE
